{
  "id": 5,
  "title": "Колокольня Смольного собора",
  "location": "Санкт-Петербург, Синопская наб.",
  "createdAt": "2024-04-09T23:53:31.913Z",
  "updatedAt": "2024-04-09T23:54:18.576Z",
  "publishedAt": "2024-04-09T23:53:33.017Z",
  "locale": "en",
  "localizations": [],
  "media": [
    {
      "id": 48,
      "name": "hero-section-bg.png",
      "alternativeText": null,
      "caption": null,
      "width": 1225,
      "height": 816,
      "formats": {
        "large": {
          "ext": ".png",
          "url": "/uploads/large_hero_section_bg_514a4c7088.png",
          "hash": "large_hero_section_bg_514a4c7088",
          "mime": "image/png",
          "name": "large_hero-section-bg.png",
          "path": null,
          "size": 1712.4,
          "width": 1000,
          "height": 666
        },
        "small": {
          "ext": ".png",
          "url": "/uploads/small_hero_section_bg_514a4c7088.png",
          "hash": "small_hero_section_bg_514a4c7088",
          "mime": "image/png",
          "name": "small_hero-section-bg.png",
          "path": null,
          "size": 462.61,
          "width": 500,
          "height": 333
        },
        "medium": {
          "ext": ".png",
          "url": "/uploads/medium_hero_section_bg_514a4c7088.png",
          "hash": "medium_hero_section_bg_514a4c7088",
          "mime": "image/png",
          "name": "medium_hero-section-bg.png",
          "path": null,
          "size": 998.05,
          "width": 750,
          "height": 500
        },
        "thumbnail": {
          "ext": ".png",
          "url": "/uploads/thumbnail_hero_section_bg_514a4c7088.png",
          "hash": "thumbnail_hero_section_bg_514a4c7088",
          "mime": "image/png",
          "name": "thumbnail_hero-section-bg.png",
          "path": null,
          "size": 112.13,
          "width": 234,
          "height": 156
        }
      },
      "hash": "hero_section_bg_514a4c7088",
      "ext": ".png",
      "mime": "image/png",
      "size": 449.73,
      "url": "/uploads/hero_section_bg_514a4c7088.png",
      "previewUrl": null,
      "provider": "local",
      "provider_metadata": null,
      "folderPath": "/",
      "createdAt": "2024-04-03T14:25:22.159Z",
      "updatedAt": "2024-04-03T14:25:22.159Z"
    }
  ],
  "page_blocks": [
    {
      "__component": "page-blocks.hero-section-block",
      "id": 23,
      "title": "Колокольня Смольного собора",
      "description": "Санкт-Петербург, Синопская наб.",
      "variant": "kultfond-media-on-right-small",
      "anchor": null,
      "class_name": null,
      "media": null,
      "buttons": [],
      "additional_media": [
        {
          "id": 48,
          "name": "hero-section-bg.png",
          "alternativeText": null,
          "caption": null,
          "width": 1225,
          "height": 816,
          "formats": {
            "large": {
              "ext": ".png",
              "url": "/uploads/large_hero_section_bg_514a4c7088.png",
              "hash": "large_hero_section_bg_514a4c7088",
              "mime": "image/png",
              "name": "large_hero-section-bg.png",
              "path": null,
              "size": 1712.4,
              "width": 1000,
              "height": 666
            },
            "small": {
              "ext": ".png",
              "url": "/uploads/small_hero_section_bg_514a4c7088.png",
              "hash": "small_hero_section_bg_514a4c7088",
              "mime": "image/png",
              "name": "small_hero-section-bg.png",
              "path": null,
              "size": 462.61,
              "width": 500,
              "height": 333
            },
            "medium": {
              "ext": ".png",
              "url": "/uploads/medium_hero_section_bg_514a4c7088.png",
              "hash": "medium_hero_section_bg_514a4c7088",
              "mime": "image/png",
              "name": "medium_hero-section-bg.png",
              "path": null,
              "size": 998.05,
              "width": 750,
              "height": 500
            },
            "thumbnail": {
              "ext": ".png",
              "url": "/uploads/thumbnail_hero_section_bg_514a4c7088.png",
              "hash": "thumbnail_hero_section_bg_514a4c7088",
              "mime": "image/png",
              "name": "thumbnail_hero-section-bg.png",
              "path": null,
              "size": 112.13,
              "width": 234,
              "height": 156
            }
          },
          "hash": "hero_section_bg_514a4c7088",
          "ext": ".png",
          "mime": "image/png",
          "size": 449.73,
          "url": "/uploads/hero_section_bg_514a4c7088.png",
          "previewUrl": null,
          "provider": "local",
          "provider_metadata": null,
          "folderPath": "/",
          "createdAt": "2024-04-03T14:25:22.159Z",
          "updatedAt": "2024-04-03T14:25:22.159Z"
        }
      ]
    },
    {
      "__component": "page-blocks.hero-section-block",
      "id": 24,
      "title": null,
      "description": "Ансамбль Смольного монастыря – один из красивейших памятников Петербурга, одна из главных достопримечательностей наряду с Исаакиевским собором, собром Воскресения Христова (Спасом- на-Крови), Казанским и Петропавловским соборами.\n\nСмольный собор – яркий пример уникального, редкого штукатурного барокко, аналогов петербургскому штукатурному барокко в мире практически нет. Ансамбль Смольного монастыря с колокольней – доказанный замысел императрицы Елизаветы Петровны и архитектора Франческо Бартоломео Растрелли.",
      "variant": "kultfond-description-light",
      "anchor": null,
      "class_name": "py-5",
      "media": null,
      "buttons": [],
      "additional_media": null
    },
    {
      "__component": "page-blocks.features-section-block",
      "id": 5,
      "title": null,
      "description": null,
      "subtitle": null,
      "variant": "kultfond-years",
      "anchor": null,
      "class_name": "pt-5 pb-36",
      "media": null,
      "additional_media": null,
      "features": [
        {
          "id": 25,
          "description": "Елизавета Петровна повелела построить на месте Смольного дворца, где прошло ее детство, «вдали от города», величественный монастырь, где она в тишине и покое завершит свои дни. В монастыре также должны были воспитываться девушки из аристократических семей. Проект был поручен придворному архитектору Франческо Бартоломео Растрелли.",
          "title": "1740",
          "subtitle": null,
          "media": null,
          "additional_media": null
        },
        {
          "id": 24,
          "description": "Начало работы над проектом. Растрелли работал над проектом ансамбля Смольного монастыря 4 года (с 1744 по 1748), выполнив в поисках наиболее выразительного решения огромное количество чертежей. Первоначально, в проекте и плане отсутствовала колокольня, она появилась лишь через год после закладки Смольного собора. ",
          "title": "1744 ",
          "subtitle": null,
          "media": null,
          "additional_media": null
        },
        {
          "id": 26,
          "description": "Начало строительства. Первыми строились кельи с восточной стороны, на берегу Невы. Через 3 месяца Елизавета Петровна повелела строить собор пятиглавым, по аналогии с Успенским собором в Кремле и возвести колокольню «против обретающейсяв Москве Ивановской також и колокола большого» – построить колокольнюподобную башне Ивана Великого в Москве и отлить огромный колокол. Растрелли было прямо предложено, чтобы Колокольня Смольного была спроектирована «противо Ивановской».\n\nКолокольня Ивана Великого, столп утверждения и славы, воздвигнутая Борисом Годуновым, была и высотно-композиционным центром Московского Кремля, и символом могущества Русского государства. \nРастрелли немедленно приступил к переделке проекта. Верхняя часть колокольни была запроектирована в виде столпа с небольшой главкой. Этот столп по своей композиционной идее перекликается со столпом Ивана Великого. Проект был переделан очень быстро.",
          "title": "1749",
          "subtitle": null,
          "media": null,
          "additional_media": null
        },
        {
          "id": 27,
          "description": "На территории будущего монастыря стали строить специальную светлицу, куда уже в 1751 перевезли начатую модель. В ней модель сохранялась до завершения строительства монастыря.\nИзготовление модели было обязательным, это давало возможность проверить все детали проекта, и уже в соответствие с моделью выполнялись все необходимые чертежи и шаблоны. Первыми в модели были сделаны жилые корпуса и угловые церкви, после них – собор и монастырская ограда, и, наконец, колокольня. Таким же был порядок возведения всех этих сооружений в натуре.\n \nСобор строился быстро, с небывалым размахом и щедрым финансированием, но с началом семилетней войны с Пруссией работы замедлились. Многоярусная колокольня должна была стать главным архитектурным ориентиром нового, только начинающегося застраиваться района, подобно Петропавловскому собору в старом центре города.\nИменно при ее возведении возникли самые большие трудности. Кроме того, что она строилась последней, императрица потребовала отлить огромный колокол весом 12 000 пудов и диаметром 6,5 метров.\nПроект колокольни был проработан, модель выполнена, фундаментготов, а строительство второго яруса откладывалось, так как не могли найти мастеров, которые взялись бы за отливку такого колокола. Предполагалось отливку произвести на фундаменте колокольни, а затем поднять ее во второй ярус и продолжить строительство. Наконец, нашли мастера Дмитрия Евдокимова, но",
          "title": "1750",
          "subtitle": null,
          "media": null,
          "additional_media": null
        },
        {
          "id": 28,
          "description": "Работы практически прекратились в связи со смертью Елизаветы Петровны. Строительство колокольни было завершено до второго из пяти запланированных ярусов.\nПосле смерти императрицы, отлучения от двора и отъезда Растрелли из России строительство встало, из-за нехватки средств было окончательно решено не строить колокольню выше уже созданных ярусов. Собор оставался недостроенным почти 70 лет.",
          "title": "1761",
          "subtitle": null,
          "media": null,
          "additional_media": null
        },
        {
          "id": 29,
          "description": "По указанию Николая I начались работы по достройке храма, а в 30-х годах XIX века остатки ярусов Колокольни были разобраны. Достройка осуществлялась по переработанному проекту Василия Стасова: заделывали трещины, латали кровлю. Фасады собора были выкрашены в желтый цвет. Собор достроили в 1835 году.",
          "title": "1820-е",
          "subtitle": null,
          "media": null,
          "additional_media": null
        }
      ]
    }
  ],
  "categories": [
    {
      "id": 1,
      "title": "В стадии реализации",
      "createdAt": "2024-04-08T21:58:51.234Z",
      "updatedAt": "2024-04-08T21:59:09.853Z",
      "publishedAt": "2024-04-08T21:58:52.745Z",
      "locale": "en"
    }
  ]
}